ws_watcher-0.6.4.dist-info/METADATA
ws_watcher-0.6.4.dist-info/WHEEL
ws_watcher-0.6.4.dist-info/entry_points.txt
ws_watcher-0.6.4.dist-info/licenses/LICENSE
ws_watcher/.ws_watcher.py.swp
ws_watcher/__init__.py
ws_watcher/ws_watcher.py
ws_watcher-0.6.4.dist-info/RECORD
